wibuapi/__init__.py
wibuapi/utils.py
wibuapi/wibuapi.py
wibuapi/wibuapi_async.py
wibuapi/zyxdevs.py
wibuapi-0.1.8.dist-info/LICENSE
wibuapi-0.1.8.dist-info/METADATA
wibuapi-0.1.8.dist-info/WHEEL
wibuapi-0.1.8.dist-info/top_level.txt
wibuapi-0.1.8.dist-info/RECORD
