Metadata-Version: 2.1
Name: wibuapi
Version: 0.1.8
Summary: Official Sync and Async Python Wrapper for Wibu API.
Home-page: https://wibu-api.eu.org
Author: Yoga Pranata
Author-email: yoga@zyxdevs.eu.org
License: MIT
Project-URL: Source, https://github.com/zYxDevs/wibu-api-py
Project-URL: Funding, https://github.com/sponsors/zYxDevs
Project-URL: Documentation, https://wibu-api.eu.org/redoc
Project-URL: Bug Tracker, https://github.com/zYxDevs/wibu-api-py/issues
Project-URL: Changelog, https://github.com/zYxDevs/wibu-api-py/releases
Keywords: wibu,weebs,otaku,anime,hentai,donghua,manga,doujin,manhwa,manhua,jdrama,jav,music,novel,api,ip,terabox,lyrics,booru,sfw,nsfw,scraper,bypasser,genshin,facebook,youtube
Classifier: Programming Language :: Python
Classifier: Programming Language :: Python :: 3
Classifier: Programming Language :: Python :: 3.8
Classifier: Programming Language :: Python :: 3.9
Classifier: Programming Language :: Python :: 3.10
Classifier: Programming Language :: Python :: 3.11
Classifier: Operating System :: OS Independent
Classifier: Development Status :: 5 - Production/Stable
Classifier: Natural Language :: English
Classifier: Topic :: Internet
Classifier: Topic :: Software Development :: Libraries
Classifier: Topic :: Software Development :: Libraries :: Python Modules
Classifier: License :: OSI Approved :: GNU Lesser General Public License v3 (LGPLv3)
Requires-Python: >=3.8
License-File: LICENSE
Requires-Dist: requests
Requires-Dist: aiohttp
